Metadata-Version: 2.1
Name: pacotepypi
Version: 0.0.2
Summary: Exemplo de pacote PyPI
Home-page: https://github.com/caiocarneloz/pacotepypi
Author: Caio Carneloz
Author-email: caiocarneloz@gmail.com
License: MIT License
Keywords: Pacote
Platform: UNKNOWN
